nethermath.py
nethermath-1.2.4.dist-info/METADATA
nethermath-1.2.4.dist-info/WHEEL
nethermath-1.2.4.dist-info/entry_points.txt
nethermath-1.2.4.dist-info/top_level.txt
nethermath-1.2.4.dist-info/RECORD
