Metadata-Version: 2.1
Name: nethermath
Version: 1.2.4
Summary: Calculator with a sophisticated concepts.
Home-page: https://github.com/saphiraaa/NetherMath
Author: Saphiraaa
Author-email: fredmarkivand@gmail.com
Classifier: Programming Language :: Python :: 3
Requires-Dist: colorama
Requires-Dist: cryptography
Requires-Dist: datetime
Requires-Dist: forex-python
Requires-Dist: ipaddress
Requires-Dist: numpy
Requires-Dist: requests
Requires-Dist: scipy
Requires-Dist: statistics
